{
  "POIs": [
    {
      "fit": [
        -2.236406087875366,
        0.699999988079071,
        5.0
      ],
      "name": "Ac"
    },
    {
      "fit": [
        0.5,
        1.0,
        1.1670361757278442
      ],
      "name": "r_neg"
    }
  ],
  "method": "default",
  "params": [
    {
      "Ac": [
        0.7841569781303406,
        0.699999988079071,
        0.4843471646308899
      ],
      "fit": [
        -0.988056480884552,
        0.0,
        0.9925530552864075
      ],
      "groups": [],
      "impact_Ac": 0.21565282344818115,
      "impact_r_neg": 0.01854097843170166,
      "name": "TTbar_norm",
      "prefit": [
        -0.9999999999999999,
        0.0,
        0.9999999999999999
      ],
      "r_neg": [
        0.9999598264694214,
        1.0,
        0.9814590215682983
      ],
      "type": "Gaussian"
    },
    {
      "Ac": [
        4.9940643310546875,
        0.699999988079071,
        4.984447002410889
      ],
      "fit": [
        -0.8102946281433105,
        0.0,
        0.6425619721412659
      ],
      "groups": [],
      "impact_Ac": 4.2940643429756165,
      "impact_r_neg": 0.4992188811302185,
      "name": "btagCferr1",
      "prefit": [
        -1.0,
        0.0,
        1.0
      ],
      "r_neg": [
        0.5007811188697815,
        1.0,
        0.5011842250823975
      ],
      "type": "Gaussian"
    },
    {
      "Ac": [
        4.481390476226807,
        0.699999988079071,
        4.999786853790283
      ],
      "fit": [
        -0.7664169669151306,
        0.0,
        0.6791393756866455
      ],
      "groups": [],
      "impact_Ac": 4.299786865711212,
      "impact_r_neg": 0.5,
      "name": "btagCferr2",
      "prefit": [
        -1.0,
        0.0,
        1.0
      ],
      "r_neg": [
        0.5130418539047241,
        1.0,
        0.5
      ],
      "type": "Gaussian"
    },
    {
      "Ac": [
        4.4622650146484375,
        0.699999988079071,
        4.833786487579346
      ],
      "fit": [
        -0.7190292477607727,
        0.0,
        0.721727728843689
      ],
      "groups": [],
      "impact_Ac": 4.133786499500275,
      "impact_r_neg": 0.49795836210250854,
      "name": "btagHfstats1",
      "prefit": [
        -1.0,
        0.0,
        1.0
      ],
      "r_neg": [
        0.5020416378974915,
        1.0,
        0.5068739056587219
      ],
      "type": "Gaussian"
    },
    {
      "Ac": [
        4.559823036193848,
        0.699999988079071,
        4.883054733276367
      ],
      "fit": [
        -0.7174504399299622,
        0.0,
        0.722866415977478
      ],
      "groups": [],
      "impact_Ac": 4.183054745197296,
      "impact_r_neg": 0.4987425208091736,
      "name": "btagHfstats2",
      "prefit": [
        -1.0,
        0.0,
        1.0
      ],
      "r_neg": [
        0.5012574791908264,
        1.0,
        0.5019300580024719
      ],
      "type": "Gaussian"
    },
    {
      "Ac": [
        4.901248931884766,
        0.699999988079071,
        4.9956841468811035
      ],
      "fit": [
        -0.7340819239616394,
        0.0,
        0.7183412313461304
      ],
      "groups": [],
      "impact_Ac": 4.2956841588020325,
      "impact_r_neg": 0.499983012676239,
      "name": "btagLf",
      "prefit": [
        -1.0,
        0.0,
        1.0
      ],
      "r_neg": [
        0.500016987323761,
        1.0,
        0.5000398755073547
      ],
      "type": "Gaussian"
    },
    {
      "Ac": [
        4.785287857055664,
        0.699999988079071,
        4.382725715637207
      ],
      "fit": [
        -0.694149374961853,
        0.0,
        0.7473845481872559
      ],
      "groups": [],
      "impact_Ac": 4.085287868976593,
      "impact_r_neg": 0.4986717104911804,
      "name": "btagLfstats2",
      "prefit": [
        -1.0,
        0.0,
        1.0
      ],
      "r_neg": [
        0.5013282895088196,
        1.0,
        0.5042384266853333
      ],
      "type": "Gaussian"
    },
    {
      "Ac": [
        4.910882949829102,
        0.699999988079071,
        4.990440368652344
      ],
      "fit": [
        -0.7318313717842102,
        0.0,
        0.708975076675415
      ],
      "groups": [],
      "impact_Ac": 4.290440380573273,
      "impact_r_neg": 0.4999406337738037,
      "name": "eleID",
      "prefit": [
        -1.0,
        0.0,
        1.0
      ],
      "r_neg": [
        0.5075070261955261,
        1.0,
        0.5000593662261963
      ],
      "type": "Gaussian"
    },
    {
      "Ac": [
        4.237395763397217,
        0.699999988079071,
        4.430237293243408
      ],
      "fit": [
        -0.7262534499168396,
        0.0,
        0.7142395377159119
      ],
      "groups": [],
      "impact_Ac": 3.730237305164337,
      "impact_r_neg": 0.49961942434310913,
      "name": "eleReco",
      "prefit": [
        -1.0,
        0.0,
        1.0
      ],
      "r_neg": [
        0.5017850399017334,
        1.0,
        0.5003805756568909
      ],
      "type": "Gaussian"
    },
    {
      "Ac": [
        4.306013584136963,
        0.699999988079071,
        4.905353546142578
      ],
      "fit": [
        -0.7466868162155151,
        0.0,
        0.6951701045036316
      ],
      "groups": [],
      "impact_Ac": 4.205353558063507,
      "impact_r_neg": 0.4987282156944275,
      "name": "eleTrigger",
      "prefit": [
        -1.0,
        0.0,
        1.0
      ],
      "r_neg": [
        0.5169612765312195,
        1.0,
        0.5012717843055725
      ],
      "type": "Gaussian"
    },
    {
      "Ac": [
        0.7403032183647156,
        0.699999988079071,
        0.6502723693847656
      ],
      "fit": [
        -0.991743266582489,
        0.0,
        0.9930505156517029
      ],
      "groups": [],
      "impact_Ac": 0.04972761869430542,
      "impact_r_neg": 0.0008895397186279297,
      "name": "fsr",
      "prefit": [
        -1.0,
        0.0,
        1.0
      ],
      "r_neg": [
        0.9999697804450989,
        1.0,
        0.9991104602813721
      ],
      "type": "Gaussian"
    },
    {
      "Ac": [
        0.7101144790649414,
        0.699999988079071,
        0.6686547994613647
      ],
      "fit": [
        -0.9931647181510925,
        0.0,
        0.9937243461608887
      ],
      "groups": [],
      "impact_Ac": 0.0313451886177063,
      "impact_r_neg": 0.0006337165832519531,
      "name": "isr",
      "prefit": [
        -1.0,
        0.0,
        1.0
      ],
      "r_neg": [
        0.9999954104423523,
        1.0,
        0.999366283416748
      ],
      "type": "Gaussian"
    },
    {
      "Ac": [
        0.7861722707748413,
        0.699999988079071,
        0.4619271457195282
      ],
      "fit": [
        -0.9874523878097534,
        0.0,
        0.9843781590461731
      ],
      "groups": [],
      "impact_Ac": 0.23807284235954285,
      "impact_r_neg": 0.012620687484741211,
      "name": "jec",
      "prefit": [
        -1.0,
        0.0,
        1.0
      ],
      "r_neg": [
        0.999998152256012,
        1.0,
        0.9873793125152588
      ],
      "type": "Gaussian"
    },
    {
      "Ac": [
        0.6903098821640015,
        0.699999988079071,
        0.7008625268936157
      ],
      "fit": [
        -0.9934248924255371,
        0.0,
        0.9941388964653015
      ],
      "groups": [],
      "impact_Ac": 0.00969010591506958,
      "impact_r_neg": 0.0002110004425048828,
      "name": "jer_UL18",
      "prefit": [
        -1.0,
        0.0,
        1.0
      ],
      "r_neg": [
        0.9997889995574951,
        1.0,
        0.9999990463256836
      ],
      "type": "Gaussian"
    },
    {
      "Ac": [
        0.7137739062309265,
        0.699999988079071,
        0.6415576934814453
      ],
      "fit": [
        -0.9910628199577332,
        0.0,
        0.9863982796669006
      ],
      "groups": [],
      "impact_Ac": 0.05844229459762573,
      "impact_r_neg": 0.008972644805908203,
      "name": "lumi",
      "prefit": [
        -0.9999999999999999,
        0.0,
        0.9999999999999999
      ],
      "r_neg": [
        0.9999226331710815,
        1.0,
        0.9910273551940918
      ],
      "type": "Gaussian"
    },
    {
      "Ac": [
        0.7232610583305359,
        0.699999988079071,
        0.6150530576705933
      ],
      "fit": [
        -0.9882665872573853,
        0.0,
        0.9817796945571899
      ],
      "groups": [],
      "impact_Ac": 0.08494693040847778,
      "impact_r_neg": 0.011353015899658203,
      "name": "lumi_corr_161718",
      "prefit": [
        -0.9999999999999999,
        0.0,
        0.9999999999999999
      ],
      "r_neg": [
        0.9999935030937195,
        1.0,
        0.9886469841003418
      ],
      "type": "Gaussian"
    },
    {
      "Ac": [
        0.7011464834213257,
        0.699999988079071,
        0.6871325969696045
      ],
      "fit": [
        -0.9941153526306152,
        0.0,
        0.9941049814224243
      ],
      "groups": [],
      "impact_Ac": 0.012867391109466553,
      "impact_r_neg": 0.0003573894500732422,
      "name": "lumi_corr_1718",
      "prefit": [
        -0.9999999999999999,
        0.0,
        0.9999999999999999
      ],
      "r_neg": [
        0.9999983310699463,
        1.0,
        0.9996426105499268
      ],
      "type": "Gaussian"
    },
    {
      "Ac": [
        0.7124701738357544,
        0.699999988079071,
        0.6458077430725098
      ],
      "fit": [
        -0.9896284937858582,
        0.0,
        0.9874957203865051
      ],
      "groups": [],
      "impact_Ac": 0.05419224500656128,
      "impact_r_neg": 0.008387982845306396,
      "name": "lumi_uncorr_18",
      "prefit": [
        -0.9999999999999999,
        0.0,
        0.9999999999999999
      ],
      "r_neg": [
        0.9999889731407166,
        1.0,
        0.9916120171546936
      ],
      "type": "Gaussian"
    },
    {
      "Ac": [
        1.1372977495193481,
        0.699999988079071,
        0.18370658159255981
      ],
      "fit": [
        -0.9939831495285034,
        0.0,
        0.9937608242034912
      ],
      "groups": [],
      "impact_Ac": 0.5162934064865112,
      "impact_r_neg": 0.00043523311614990234,
      "name": "murmuf",
      "prefit": [
        -1.0,
        0.0,
        1.0
      ],
      "r_neg": [
        0.9997490048408508,
        1.0,
        0.9995647668838501
      ],
      "type": "Gaussian"
    },
    {
      "Ac": [
        0.7007067799568176,
        0.699999988079071,
        0.6992228031158447
      ],
      "fit": [
        -0.9940875768661499,
        0.0,
        0.9943830370903015
      ],
      "groups": [],
      "impact_Ac": 0.0007771849632263184,
      "impact_r_neg": 7.748603820800781e-07,
      "name": "pdf",
      "prefit": [
        -1.0,
        0.0,
        1.0
      ],
      "r_neg": [
        0.9999992251396179,
        1.0,
        0.9999999403953552
      ],
      "type": "Gaussian"
    },
    {
      "Ac": [
        4.7737650871276855,
        0.699999988079071,
        4.486851692199707
      ],
      "fit": [
        -0.7199429273605347,
        0.0,
        0.7200961709022522
      ],
      "groups": [],
      "impact_Ac": 4.0737650990486145,
      "impact_r_neg": 0.49922120571136475,
      "name": "prefiringWeight",
      "prefit": [
        -1.0,
        0.0,
        1.0
      ],
      "r_neg": [
        0.5007787942886353,
        1.0,
        0.5064440369606018
      ],
      "type": "Gaussian"
    },
    {
      "Ac": [
        -0.9767759442329407,
        0.699999988079071,
        2.4729244709014893
      ],
      "fit": [
        240.49147033691406,
        256.0,
        272.0231018066406
      ],
      "groups": [],
      "impact_Ac": 1.7729244828224182,
      "impact_r_neg": 0.0049430131912231445,
      "name": "prop_binele_UL18_SR_bin0_Others",
      "prefit": [
        240.3316383744344,
        256.0,
        272.33514435597954
      ],
      "r_neg": [
        0.9994716644287109,
        1.0,
        0.9950569868087769
      ],
      "type": "Poisson"
    },
    {
      "Ac": [
        0.6917780041694641,
        0.699999988079071,
        0.7090003490447998
      ],
      "fit": [
        415275.9375,
        415917.0,
        416558.53125
      ],
      "groups": [],
      "impact_Ac": 0.00900036096572876,
      "impact_r_neg": 2.8312206268310547e-05,
      "name": "prop_binele_UL18_SR_bin0_ST",
      "prefit": [
        415272.4160842112,
        415917.0,
        416562.2483756267
      ],
      "r_neg": [
        0.9999924898147583,
        1.0,
        0.9999716877937317
      ],
      "type": "Poisson"
    },
    {
      "Ac": [
        0.6900444626808167,
        0.699999988079071,
        0.7094067931175232
      ],
      "fit": [
        -0.9939279556274414,
        0.0,
        0.9943159818649292
      ],
      "groups": [],
      "impact_Ac": 0.009955525398254395,
      "impact_r_neg": 2.9742717742919922e-05,
      "name": "prop_binele_UL18_SR_bin0_TTbar_1",
      "prefit": [
        -0.9999999999999999,
        0.0,
        0.9999999999999999
      ],
      "r_neg": [
        0.9999999403953552,
        1.0,
        0.9999702572822571
      ],
      "type": "Gaussian"
    },
    {
      "Ac": [
        0.6978163123130798,
        0.699999988079071,
        0.7023651003837585
      ],
      "fit": [
        131587.109375,
        131948.0,
        132309.5625
      ],
      "groups": [],
      "impact_Ac": 0.0023651123046875,
      "impact_r_neg": 7.927417755126953e-06,
      "name": "prop_binele_UL18_SR_bin0_TTbar_2",
      "prefit": [
        131585.08596895862,
        131948.0,
        132311.57845882568
      ],
      "r_neg": [
        0.9999977350234985,
        1.0,
        0.9999920725822449
      ],
      "type": "Poisson"
    },
    {
      "Ac": [
        2.408942699432373,
        0.699999988079071,
        -1.1374671459197998
      ],
      "fit": [
        253.04971313476562,
        269.0,
        285.6275329589844
      ],
      "groups": [],
      "impact_Ac": 1.8374671339988708,
      "impact_r_neg": 0.0010507702827453613,
      "name": "prop_binele_UL18_SR_bin1_Others",
      "prefit": [
        252.9304587527169,
        269.0000003339183,
        285.7363185149068
      ],
      "r_neg": [
        0.9999656081199646,
        1.0,
        0.9989492297172546
      ],
      "type": "Poisson"
    },
    {
      "Ac": [
        0.7092494368553162,
        0.699999988079071,
        0.691182553768158
      ],
      "fit": [
        334794.5625,
        335370.0,
        335946.03125
      ],
      "groups": [],
      "impact_Ac": 0.009249448776245117,
      "impact_r_neg": 1.5795230865478516e-05,
      "name": "prop_binele_UL18_SR_bin1_ST",
      "prefit": [
        334791.2208812642,
        335369.9999299956,
        335949.443371542
      ],
      "r_neg": [
        0.9999933838844299,
        1.0,
        0.9999842047691345
      ],
      "type": "Poisson"
    },
    {
      "Ac": [
        0.7022457718849182,
        0.699999988079071,
        0.6970646381378174
      ],
      "fit": [
        132647.65625,
        133010.0,
        133373.015625
      ],
      "groups": [],
      "impact_Ac": 0.002935349941253662,
      "impact_r_neg": 5.125999450683594e-06,
      "name": "prop_binele_UL18_SR_bin1_TTbar_1",
      "prefit": [
        132645.62704969366,
        133010.0,
        133375.0373167761
      ],
      "r_neg": [
        0.9999959468841553,
        1.0,
        0.9999948740005493
      ],
      "type": "Poisson"
    },
    {
      "Ac": [
        0.7088099122047424,
        0.699999988079071,
        0.6882500052452087
      ],
      "fit": [
        -0.9939636588096619,
        0.0,
        0.9943141937255859
      ],
      "groups": [],
      "impact_Ac": 0.011749982833862305,
      "impact_r_neg": 2.1576881408691406e-05,
      "name": "prop_binele_UL18_SR_bin1_TTbar_2",
      "prefit": [
        -0.9999999999999999,
        0.0,
        0.9999999999999999
      ],
      "r_neg": [
        0.9999784231185913,
        1.0,
        0.9999809265136719
      ],
      "type": "Gaussian"
    },
    {
      "Ac": [
        3.768482208251953,
        0.699999988079071,
        4.917642593383789
      ],
      "fit": [
        -0.7309924364089966,
        0.0,
        0.699236273765564
      ],
      "groups": [],
      "impact_Ac": 4.217642605304718,
      "impact_r_neg": 0.4999741315841675,
      "name": "pu",
      "prefit": [
        -1.0,
        0.0,
        1.0
      ],
      "r_neg": [
        0.5001586079597473,
        1.0,
        0.5000258684158325
      ],
      "type": "Gaussian"
    },
    {
      "Ac": [
        4.665300369262695,
        0.699999988079071,
        4.886043548583984
      ],
      "fit": [
        -0.7206123471260071,
        0.0,
        0.7197881937026978
      ],
      "groups": [],
      "impact_Ac": 4.186043560504913,
      "impact_r_neg": 0.4953877925872803,
      "name": "tmistag",
      "prefit": [
        -1.0,
        0.0,
        1.0
      ],
      "r_neg": [
        0.5046122074127197,
        1.0,
        0.510897159576416
      ],
      "type": "Gaussian"
    },
    {
      "Ac": [
        4.322831153869629,
        0.699999988079071,
        4.37835168838501
      ],
      "fit": [
        -0.7210296988487244,
        0.0,
        0.7199621200561523
      ],
      "groups": [],
      "impact_Ac": 3.6783517003059387,
      "impact_r_neg": 0.4982949495315552,
      "name": "ttagUncorr",
      "prefit": [
        -1.0,
        0.0,
        1.0
      ],
      "r_neg": [
        0.5075969099998474,
        1.0,
        0.5017050504684448
      ],
      "type": "Gaussian"
    }
  ]
}