{
  "POIs": [
    {
      "fit": [
        -5.0,
        0.5,
        5.0
      ],
      "name": "Ac"
    },
    {
      "fit": [
        0.5,
        1.0,
        1.1819355487823486
      ],
      "name": "r_neg"
    }
  ],
  "method": "default",
  "params": [
    {
      "Ac": [
        0.785814106464386,
        0.5,
        -0.2549055814743042
      ],
      "fit": [
        -0.9918043613433838,
        0.0,
        0.9931308031082153
      ],
      "groups": [],
      "impact_Ac": 0.7549055814743042,
      "impact_r_neg": 0.034091174602508545,
      "name": "TTbar_norm",
      "prefit": [
        -0.9999999999999999,
        0.0,
        0.9999999999999999
      ],
      "r_neg": [
        1.0096179246902466,
        1.0,
        0.9659088253974915
      ],
      "type": "Gaussian"
    },
    {
      "Ac": [
        -1.1893677711486816,
        0.5,
        -4.672942161560059
      ],
      "fit": [
        -0.29981204867362976,
        0.0,
        0.28069406747817993
      ],
      "groups": [],
      "impact_Ac": 5.172942161560059,
      "impact_r_neg": 0.06019020080566406,
      "name": "btagCferr1",
      "prefit": [
        -1.0,
        0.0,
        1.0
      ],
      "r_neg": [
        1.060190200805664,
        1.0,
        0.9784191250801086
      ],
      "type": "Gaussian"
    },
    {
      "Ac": [
        -0.355983704328537,
        0.5,
        -4.982149600982666
      ],
      "fit": [
        -0.2949749529361725,
        0.0,
        0.2901513874530792
      ],
      "groups": [],
      "impact_Ac": 5.482149600982666,
      "impact_r_neg": 0.04715836048126221,
      "name": "btagCferr2",
      "prefit": [
        -1.0,
        0.0,
        1.0
      ],
      "r_neg": [
        1.0471583604812622,
        1.0,
        0.9953905344009399
      ],
      "type": "Gaussian"
    },
    {
      "Ac": [
        -0.20129990577697754,
        0.5,
        0.6948073506355286
      ],
      "fit": [
        -0.25647303462028503,
        0.0,
        0.28404781222343445
      ],
      "groups": [],
      "impact_Ac": 0.7012999057769775,
      "impact_r_neg": 0.023472905158996582,
      "name": "btagHf",
      "prefit": [
        -1.0,
        0.0,
        1.0
      ],
      "r_neg": [
        1.0234729051589966,
        1.0,
        0.9907394051551819
      ],
      "type": "Gaussian"
    },
    {
      "Ac": [
        -0.11237750202417374,
        0.5,
        -0.2033540904521942
      ],
      "fit": [
        -0.2924197316169739,
        0.0,
        0.29209649562835693
      ],
      "groups": [],
      "impact_Ac": 0.7033540904521942,
      "impact_r_neg": 0.017215371131896973,
      "name": "btagHfstats1",
      "prefit": [
        -1.0,
        0.0,
        1.0
      ],
      "r_neg": [
        1.0143918991088867,
        1.0,
        1.017215371131897
      ],
      "type": "Gaussian"
    },
    {
      "Ac": [
        -0.19127516448497772,
        0.5,
        -0.18471665680408478
      ],
      "fit": [
        -0.29134517908096313,
        0.0,
        0.2926785945892334
      ],
      "groups": [],
      "impact_Ac": 0.6912751644849777,
      "impact_r_neg": 0.016276001930236816,
      "name": "btagHfstats2",
      "prefit": [
        -1.0,
        0.0,
        1.0
      ],
      "r_neg": [
        1.0150599479675293,
        1.0,
        1.0162760019302368
      ],
      "type": "Gaussian"
    },
    {
      "Ac": [
        -0.0836094319820404,
        0.5,
        -0.0025936677120625973
      ],
      "fit": [
        -0.2893907427787781,
        0.0,
        0.2909126579761505
      ],
      "groups": [],
      "impact_Ac": 0.5836094319820404,
      "impact_r_neg": 0.024453401565551758,
      "name": "btagLf",
      "prefit": [
        -1.0,
        0.0,
        1.0
      ],
      "r_neg": [
        1.0244534015655518,
        1.0,
        1.009735345840454
      ],
      "type": "Gaussian"
    },
    {
      "Ac": [
        0.2913600206375122,
        0.5,
        0.037144098430871964
      ],
      "fit": [
        -0.2852097153663635,
        0.0,
        0.2991625964641571
      ],
      "groups": [],
      "impact_Ac": 0.46285590156912804,
      "impact_r_neg": 0.02135634422302246,
      "name": "btagLfstats1",
      "prefit": [
        -1.0,
        0.0,
        1.0
      ],
      "r_neg": [
        0.9947736859321594,
        1.0,
        1.0213563442230225
      ],
      "type": "Gaussian"
    },
    {
      "Ac": [
        0.27713197469711304,
        0.5,
        0.04145639017224312
      ],
      "fit": [
        -0.2851259112358093,
        0.0,
        0.2989051938056946
      ],
      "groups": [],
      "impact_Ac": 0.4585436098277569,
      "impact_r_neg": 0.018347501754760742,
      "name": "btagLfstats2",
      "prefit": [
        -1.0,
        0.0,
        1.0
      ],
      "r_neg": [
        0.9975816607475281,
        1.0,
        1.0183475017547607
      ],
      "type": "Gaussian"
    },
    {
      "Ac": [
        0.5328060388565063,
        0.5,
        0.36776700615882874
      ],
      "fit": [
        -0.9930113554000854,
        0.0,
        0.9931885600090027
      ],
      "groups": [],
      "impact_Ac": 0.13223299384117126,
      "impact_r_neg": 0.00370943546295166,
      "name": "fsr",
      "prefit": [
        -1.0,
        0.0,
        1.0
      ],
      "r_neg": [
        1.0025345087051392,
        1.0,
        0.9962905645370483
      ],
      "type": "Gaussian"
    },
    {
      "Ac": [
        -4.672510623931885,
        0.5,
        -4.628559589385986
      ],
      "fit": [
        -0.165705606341362,
        0.0,
        0.1663709580898285
      ],
      "groups": [],
      "impact_Ac": 5.172510623931885,
      "impact_r_neg": 0.49986714124679565,
      "name": "hdamp",
      "prefit": [
        -1.0,
        0.0,
        1.0
      ],
      "r_neg": [
        0.5001917481422424,
        1.0,
        0.5001328587532043
      ],
      "type": "Gaussian"
    },
    {
      "Ac": [
        0.5587818622589111,
        0.5,
        0.4204753637313843
      ],
      "fit": [
        -0.9940546751022339,
        0.0,
        0.9938812851905823
      ],
      "groups": [],
      "impact_Ac": 0.07952463626861572,
      "impact_r_neg": 0.0017664432525634766,
      "name": "isr",
      "prefit": [
        -1.0,
        0.0,
        1.0
      ],
      "r_neg": [
        1.0010380744934082,
        1.0,
        0.9982335567474365
      ],
      "type": "Gaussian"
    },
    {
      "Ac": [
        0.48772475123405457,
        0.5,
        0.3825802206993103
      ],
      "fit": [
        -0.9853924512863159,
        0.0,
        0.9763028621673584
      ],
      "groups": [],
      "impact_Ac": 0.1174197793006897,
      "impact_r_neg": 0.016211986541748047,
      "name": "jec",
      "prefit": [
        -1.0,
        0.0,
        1.0
      ],
      "r_neg": [
        1.0073715448379517,
        1.0,
        0.983788013458252
      ],
      "type": "Gaussian"
    },
    {
      "Ac": [
        0.3824440538883209,
        0.5,
        0.5096189379692078
      ],
      "fit": [
        -0.9940576553344727,
        0.0,
        0.993401288986206
      ],
      "groups": [],
      "impact_Ac": 0.11755594611167908,
      "impact_r_neg": 0.0020737648010253906,
      "name": "jer_UL18",
      "prefit": [
        -1.0,
        0.0,
        1.0
      ],
      "r_neg": [
        0.9979262351989746,
        1.0,
        1.0010545253753662
      ],
      "type": "Gaussian"
    },
    {
      "Ac": [
        0.5464070439338684,
        0.5,
        0.23720815777778625
      ],
      "fit": [
        -0.9902778267860413,
        0.0,
        0.9902583360671997
      ],
      "groups": [],
      "impact_Ac": 0.26279184222221375,
      "impact_r_neg": 0.010807454586029053,
      "name": "lumi",
      "prefit": [
        -0.9999999999999999,
        0.0,
        0.9999999999999999
      ],
      "r_neg": [
        1.000190019607544,
        1.0,
        0.989192545413971
      ],
      "type": "Gaussian"
    },
    {
      "Ac": [
        0.597075879573822,
        0.5,
        0.09939492493867874
      ],
      "fit": [
        -0.9893977046012878,
        0.0,
        0.9878312349319458
      ],
      "groups": [],
      "impact_Ac": 0.40060507506132126,
      "impact_r_neg": 0.01318281888961792,
      "name": "lumi_corr_161718",
      "prefit": [
        -0.9999999999999999,
        0.0,
        0.9999999999999999
      ],
      "r_neg": [
        1.0009689331054688,
        1.0,
        0.9868171811103821
      ],
      "type": "Gaussian"
    },
    {
      "Ac": [
        0.5014978647232056,
        0.5,
        0.4729308485984802
      ],
      "fit": [
        -0.9941478967666626,
        0.0,
        0.9938432574272156
      ],
      "groups": [],
      "impact_Ac": 0.027069151401519775,
      "impact_r_neg": 0.0006493330001831055,
      "name": "lumi_corr_1718",
      "prefit": [
        -0.9999999999999999,
        0.0,
        0.9999999999999999
      ],
      "r_neg": [
        0.999902069568634,
        1.0,
        0.9993506669998169
      ],
      "type": "Gaussian"
    },
    {
      "Ac": [
        0.5410062670707703,
        0.5,
        0.2188066691160202
      ],
      "fit": [
        -0.9898236393928528,
        0.0,
        0.9907745122909546
      ],
      "groups": [],
      "impact_Ac": 0.2811933308839798,
      "impact_r_neg": 0.009521782398223877,
      "name": "lumi_uncorr_18",
      "prefit": [
        -0.9999999999999999,
        0.0,
        0.9999999999999999
      ],
      "r_neg": [
        1.000098466873169,
        1.0,
        0.9904782176017761
      ],
      "type": "Gaussian"
    },
    {
      "Ac": [
        -0.1654595285654068,
        0.5,
        -0.14667125046253204
      ],
      "fit": [
        -0.2920978367328644,
        0.0,
        0.29246631264686584
      ],
      "groups": [],
      "impact_Ac": 0.6654595285654068,
      "impact_r_neg": 0.01602470874786377,
      "name": "muonIDStat",
      "prefit": [
        -1.0,
        0.0,
        1.0
      ],
      "r_neg": [
        1.015470266342163,
        1.0,
        1.0160247087478638
      ],
      "type": "Gaussian"
    },
    {
      "Ac": [
        -0.12560494244098663,
        0.5,
        -0.25549688935279846
      ],
      "fit": [
        -0.2928016483783722,
        0.0,
        0.2926788926124573
      ],
      "groups": [],
      "impact_Ac": 0.7554968893527985,
      "impact_r_neg": 0.016549110412597656,
      "name": "muonIDSyst",
      "prefit": [
        -1.0,
        0.0,
        1.0
      ],
      "r_neg": [
        1.0158454179763794,
        1.0,
        1.0165491104125977
      ],
      "type": "Gaussian"
    },
    {
      "Ac": [
        -0.22225695848464966,
        0.5,
        -0.13533587753772736
      ],
      "fit": [
        -0.292145699262619,
        0.0,
        0.29255491495132446
      ],
      "groups": [],
      "impact_Ac": 0.7222569584846497,
      "impact_r_neg": 0.016075611114501953,
      "name": "muonIsoStat",
      "prefit": [
        -1.0,
        0.0,
        1.0
      ],
      "r_neg": [
        1.015708088874817,
        1.0,
        1.016075611114502
      ],
      "type": "Gaussian"
    },
    {
      "Ac": [
        -0.15029430389404297,
        0.5,
        -0.12559451162815094
      ],
      "fit": [
        -0.2919928729534149,
        0.0,
        0.2920629680156708
      ],
      "groups": [],
      "impact_Ac": 0.650294303894043,
      "impact_r_neg": 0.015622258186340332,
      "name": "muonIsoSyst",
      "prefit": [
        -1.0,
        0.0,
        1.0
      ],
      "r_neg": [
        1.0154517889022827,
        1.0,
        1.0156222581863403
      ],
      "type": "Gaussian"
    },
    {
      "Ac": [
        -0.13563305139541626,
        0.5,
        -0.2556435167789459
      ],
      "fit": [
        -0.2927590608596802,
        0.0,
        0.2925659716129303
      ],
      "groups": [],
      "impact_Ac": 0.7556435167789459,
      "impact_r_neg": 0.016396760940551758,
      "name": "muonTriggerStat",
      "prefit": [
        -1.0,
        0.0,
        1.0
      ],
      "r_neg": [
        1.0158522129058838,
        1.0,
        1.0163967609405518
      ],
      "type": "Gaussian"
    },
    {
      "Ac": [
        -0.2502036690711975,
        0.5,
        -0.13524532318115234
      ],
      "fit": [
        -0.2928731441497803,
        0.0,
        0.29197055101394653
      ],
      "groups": [],
      "impact_Ac": 0.7502036690711975,
      "impact_r_neg": 0.0161440372467041,
      "name": "muonTriggerSyst",
      "prefit": [
        -1.0,
        0.0,
        1.0
      ],
      "r_neg": [
        1.016144037246704,
        1.0,
        1.0156888961791992
      ],
      "type": "Gaussian"
    },
    {
      "Ac": [
        0.5182974934577942,
        0.5,
        0.4875671863555908
      ],
      "fit": [
        -0.9941681623458862,
        0.0,
        0.9939618706703186
      ],
      "groups": [],
      "impact_Ac": 0.01829749345779419,
      "impact_r_neg": 2.1576881408691406e-05,
      "name": "murmuf",
      "prefit": [
        -1.0,
        0.0,
        1.0
      ],
      "r_neg": [
        0.9999843835830688,
        1.0,
        1.0000215768814087
      ],
      "type": "Gaussian"
    },
    {
      "Ac": [
        0.5003848075866699,
        0.5,
        0.49957382678985596
      ],
      "fit": [
        -0.9940868020057678,
        0.0,
        0.9943844079971313
      ],
      "groups": [],
      "impact_Ac": 0.00042617321014404297,
      "impact_r_neg": 2.384185791015625e-07,
      "name": "pdf",
      "prefit": [
        -1.0,
        0.0,
        1.0
      ],
      "r_neg": [
        1.000000238418579,
        1.0,
        0.9999997615814209
      ],
      "type": "Gaussian"
    },
    {
      "Ac": [
        -0.1552283763885498,
        0.5,
        -0.1769219934940338
      ],
      "fit": [
        -0.29209762811660767,
        0.0,
        0.29259738326072693
      ],
      "groups": [],
      "impact_Ac": 0.6769219934940338,
      "impact_r_neg": 0.015793681144714355,
      "name": "prefiringWeight",
      "prefit": [
        -1.0,
        0.0,
        1.0
      ],
      "r_neg": [
        1.0157936811447144,
        1.0,
        1.0157856941223145
      ],
      "type": "Gaussian"
    },
    {
      "Ac": [
        -0.06314080208539963,
        0.5,
        0.9979604482650757
      ],
      "fit": [
        3346.123779296875,
        3402.0,
        3457.551025390625
      ],
      "groups": [],
      "impact_Ac": 0.5631408020853996,
      "impact_r_neg": 0.008234977722167969,
      "name": "prop_binmuon_UL18_0_500_CR1_bin0_Others",
      "prefit": [
        3344.0069678223213,
        3402.0,
        3460.660488260026
      ],
      "r_neg": [
        0.9937690496444702,
        1.0,
        1.008234977722168
      ],
      "type": "Poisson"
    },
    {
      "Ac": [
        0.498554527759552,
        0.5,
        0.5004945397377014
      ],
      "fit": [
        515.26513671875,
        538.0,
        561.3806762695312
      ],
      "groups": [],
      "impact_Ac": 0.001445472240447998,
      "impact_r_neg": 3.820657730102539e-05,
      "name": "prop_binmuon_UL18_0_500_CR1_bin0_TTbar_1",
      "prefit": [
        515.1373232624014,
        538.000000357536,
        561.5294004287093
      ],
      "r_neg": [
        0.999961793422699,
        1.0,
        1.0000053644180298
      ],
      "type": "Poisson"
    },
    {
      "Ac": [
        0.4999934136867523,
        0.5,
        0.5002185106277466
      ],
      "fit": [
        48.88624572753906,
        56.0,
        63.7728271484375
      ],
      "groups": [],
      "impact_Ac": 0.00021851062774658203,
      "impact_r_neg": 2.6226043701171875e-06,
      "name": "prop_binmuon_UL18_0_500_CR1_bin0_TTbar_2",
      "prefit": [
        48.84658563082191,
        56.0,
        63.820611690900556
      ],
      "r_neg": [
        0.9999999403953552,
        1.0,
        1.0000026226043701
      ],
      "type": "Poisson"
    },
    {
      "Ac": [
        1.9922133684158325,
        0.5,
        -1.0361952781677246
      ],
      "fit": [
        313.4184875488281,
        329.0,
        345.0638732910156
      ],
      "groups": [],
      "impact_Ac": 1.5361952781677246,
      "impact_r_neg": 0.004016458988189697,
      "name": "prop_binmuon_UL18_0_500_CR1_bin1_Others",
      "prefit": [
        311.19347409714265,
        329.0,
        347.47328358435306
      ],
      "r_neg": [
        1.003298282623291,
        1.0,
        0.9959835410118103
      ],
      "type": "Poisson"
    },
    {
      "Ac": [
        0.5002189874649048,
        0.5,
        0.4995843768119812
      ],
      "fit": [
        54.49726486206055,
        62.0,
        70.16128540039062
      ],
      "groups": [],
      "impact_Ac": 0.00041562318801879883,
      "impact_r_neg": 2.562999725341797e-06,
      "name": "prop_binmuon_UL18_0_500_CR1_bin1_TTbar_1",
      "prefit": [
        54.456043853821924,
        62.0,
        70.21110094162034
      ],
      "r_neg": [
        1.000001072883606,
        1.0,
        0.9999974370002747
      ],
      "type": "Poisson"
    },
    {
      "Ac": [
        0.5002135038375854,
        0.5,
        0.49817711114883423
      ],
      "fit": [
        557.3927612304688,
        581.0,
        605.250732421875
      ],
      "groups": [],
      "impact_Ac": 0.0018228888511657715,
      "impact_r_neg": 1.0609626770019531e-05,
      "name": "prop_binmuon_UL18_0_500_CR1_bin1_TTbar_2",
      "prefit": [
        557.2282522558796,
        581.0,
        605.4384674849774
      ],
      "r_neg": [
        0.9999905228614807,
        1.0,
        0.99998939037323
      ],
      "type": "Poisson"
    },
    {
      "Ac": [
        -0.8324502110481262,
        0.5,
        1.766164779663086
      ],
      "fit": [
        1041.8284912109375,
        1061.0,
        1080.1973876953125
      ],
      "groups": [],
      "impact_Ac": 1.3324502110481262,
      "impact_r_neg": 0.02624034881591797,
      "name": "prop_binmuon_UL18_0_500_CR2_bin0_Others",
      "prefit": [
        1028.759490266207,
        1061.0,
        1093.9072071576984
      ],
      "r_neg": [
        0.9779092073440552,
        1.0,
        1.026240348815918
      ],
      "type": "Poisson"
    },
    {
      "Ac": [
        0.49852293729782104,
        0.5,
        0.50190269947052
      ],
      "fit": [
        5653.09033203125,
        5728.0,
        5803.572265625
      ],
      "groups": [],
      "impact_Ac": 0.0019026994705200195,
      "impact_r_neg": 2.5391578674316406e-05,
      "name": "prop_binmuon_UL18_0_500_CR2_bin0_TTbar_1",
      "prefit": [
        5652.649751849622,
        5728.0,
        5804.017261366998
      ],
      "r_neg": [
        0.9999796152114868,
        1.0,
        1.0000253915786743
      ],
      "type": "Poisson"
    },
    {
      "Ac": [
        0.49931204319000244,
        0.5,
        0.5007961392402649
      ],
      "fit": [
        1137.303466796875,
        1171.0,
        1205.357421875
      ],
      "groups": [],
      "impact_Ac": 0.0007961392402648926,
      "impact_r_neg": 1.049041748046875e-05,
      "name": "prop_binmuon_UL18_0_500_CR2_bin0_TTbar_2",
      "prefit": [
        1137.112648170798,
        1171.0,
        1205.5540467217866
      ],
      "r_neg": [
        0.9999898076057434,
        1.0,
        1.0000104904174805
      ],
      "type": "Poisson"
    },
    {
      "Ac": [
        1.0683821439743042,
        0.5,
        -0.6234131455421448
      ],
      "fit": [
        2348.3896484375,
        2389.0,
        2429.660888671875
      ],
      "groups": [],
      "impact_Ac": 1.1234131455421448,
      "impact_r_neg": 0.049653053283691406,
      "name": "prop_binmuon_UL18_0_500_CR2_bin1_Others",
      "prefit": [
        2340.4565163329457,
        2389.0,
        2438.2113146075094
      ],
      "r_neg": [
        0.9567833542823792,
        1.0,
        1.0496530532836914
      ],
      "type": "Poisson"
    },
    {
      "Ac": [
        0.49945202469825745,
        0.5,
        0.50051349401474
      ],
      "fit": [
        1090.0064697265625,
        1123.0,
        1156.652099609375
      ],
      "groups": [],
      "impact_Ac": 0.0005479753017425537,
      "impact_r_neg": 1.0311603546142578e-05,
      "name": "prop_binmuon_UL18_0_500_CR2_bin1_TTbar_1",
      "prefit": [
        1089.821316443759,
        1123.000000387594,
        1156.8453794920865
      ],
      "r_neg": [
        0.9999896883964539,
        1.0,
        1.0000089406967163
      ],
      "type": "Poisson"
    },
    {
      "Ac": [
        0.4990350902080536,
        0.5,
        0.5013928413391113
      ],
      "fit": [
        5742.48583984375,
        5818.0,
        5894.1845703125
      ],
      "groups": [],
      "impact_Ac": 0.0013928413391113281,
      "impact_r_neg": 2.300739288330078e-05,
      "name": "prop_binmuon_UL18_0_500_CR2_bin1_TTbar_2",
      "prefit": [
        5742.057479125415,
        5818.0,
        5894.609522033936
      ],
      "r_neg": [
        0.9999769926071167,
        1.0,
        1.0000226497650146
      ],
      "type": "Poisson"
    },
    {
      "Ac": [
        -4.986672401428223,
        0.5,
        4.985550880432129
      ],
      "fit": [
        507.5704345703125,
        530.0,
        552.5829467773438
      ],
      "groups": [],
      "impact_Ac": 5.486672401428223,
      "impact_r_neg": 0.10408645868301392,
      "name": "prop_binmuon_UL18_0_500_SR_bin0_Others",
      "prefit": [
        507.31041273181773,
        530.0,
        553.3563117649024
      ],
      "r_neg": [
        1.0453070402145386,
        1.0,
        0.8959135413169861
      ],
      "type": "Poisson"
    },
    {
      "Ac": [
        0.4815172255039215,
        0.5,
        0.5178002119064331
      ],
      "fit": [
        312791.875,
        313348.0,
        313904.875
      ],
      "groups": [],
      "impact_Ac": 0.01848277449607849,
      "impact_r_neg": 0.00010794401168823242,
      "name": "prop_binmuon_UL18_0_500_SR_bin0_TTbar_1",
      "prefit": [
        312788.55740242853,
        313348.0,
        313908.1070162009
      ],
      "r_neg": [
        1.0000450611114502,
        1.0,
        0.9998920559883118
      ],
      "type": "Poisson"
    },
    {
      "Ac": [
        0.4939894378185272,
        0.5,
        0.5062126517295837
      ],
      "fit": [
        46213.12109375,
        46427.0,
        46641.60546875
      ],
      "groups": [],
      "impact_Ac": 0.00621265172958374,
      "impact_r_neg": 4.023313522338867e-05,
      "name": "prop_binmuon_UL18_0_500_SR_bin0_TTbar_2",
      "prefit": [
        46211.86332550411,
        46427.0,
        46642.80106794938
      ],
      "r_neg": [
        1.0000145435333252,
        1.0,
        0.9999597668647766
      ],
      "type": "Poisson"
    },
    {
      "Ac": [
        4.995181083679199,
        0.5,
        -4.999532222747803
      ],
      "fit": [
        191.1446533203125,
        203.0,
        215.1802215576172
      ],
      "groups": [],
      "impact_Ac": 5.499532222747803,
      "impact_r_neg": 0.04582512378692627,
      "name": "prop_binmuon_UL18_0_500_SR_bin1_Others",
      "prefit": [
        189.08363263042335,
        203.00000033358882,
        217.5831796804772
      ],
      "r_neg": [
        1.0089173316955566,
        1.0,
        0.9541748762130737
      ],
      "type": "Poisson"
    },
    {
      "Ac": [
        0.507820188999176,
        0.5,
        0.48994675278663635
      ],
      "fit": [
        46348.8046875,
        46563.0,
        46777.9140625
      ],
      "groups": [],
      "impact_Ac": 0.010053247213363647,
      "impact_r_neg": 3.11732292175293e-05,
      "name": "prop_binmuon_UL18_0_500_SR_bin1_TTbar_1",
      "prefit": [
        46347.54796546693,
        46563.0,
        46779.11642802188
      ],
      "r_neg": [
        1.0000048875808716,
        1.0,
        0.9999688267707825
      ],
      "type": "Poisson"
    },
    {
      "Ac": [
        0.5237104892730713,
        0.5,
        0.471422016620636
      ],
      "fit": [
        314638.21875,
        315196.0,
        315754.5
      ],
      "groups": [],
      "impact_Ac": 0.028577983379364014,
      "impact_r_neg": 7.849931716918945e-05,
      "name": "prop_binmuon_UL18_0_500_SR_bin1_TTbar_2",
      "prefit": [
        314634.9091440778,
        315196.0,
        315757.755232002
      ],
      "r_neg": [
        1.0000091791152954,
        1.0,
        0.9999215006828308
      ],
      "type": "Poisson"
    },
    {
      "Ac": [
        1.4240554571151733,
        0.5,
        -4.8453145027160645
      ],
      "fit": [
        -0.2929883599281311,
        0.0,
        0.2898061275482178
      ],
      "groups": [],
      "impact_Ac": 5.3453145027160645,
      "impact_r_neg": 0.029095888137817383,
      "name": "pu",
      "prefit": [
        -1.0,
        0.0,
        1.0
      ],
      "r_neg": [
        0.9992698431015015,
        1.0,
        1.0290958881378174
      ],
      "type": "Gaussian"
    },
    {
      "Ac": [
        -0.22130239009857178,
        0.5,
        -0.251574844121933
      ],
      "fit": [
        -0.292174756526947,
        0.0,
        0.2925940155982971
      ],
      "groups": [],
      "impact_Ac": 0.751574844121933,
      "impact_r_neg": 0.015956878662109375,
      "name": "tmistag",
      "prefit": [
        -1.0,
        0.0,
        1.0
      ],
      "r_neg": [
        1.0158783197402954,
        1.0,
        1.0159568786621094
      ],
      "type": "Gaussian"
    },
    {
      "Ac": [
        -0.18546710908412933,
        0.5,
        -0.14896202087402344
      ],
      "fit": [
        -0.2923179864883423,
        0.0,
        0.29240724444389343
      ],
      "groups": [],
      "impact_Ac": 0.6854671090841293,
      "impact_r_neg": 0.01588571071624756,
      "name": "ttagCorr",
      "prefit": [
        -1.0,
        0.0,
        1.0
      ],
      "r_neg": [
        1.0158295631408691,
        1.0,
        1.0158857107162476
      ],
      "type": "Gaussian"
    },
    {
      "Ac": [
        -0.1741722822189331,
        0.5,
        -0.14884568750858307
      ],
      "fit": [
        -0.2923181653022766,
        0.0,
        0.2924075722694397
      ],
      "groups": [],
      "impact_Ac": 0.6741722822189331,
      "impact_r_neg": 0.01588618755340576,
      "name": "ttagUncorr",
      "prefit": [
        -1.0,
        0.0,
        1.0
      ],
      "r_neg": [
        1.0158154964447021,
        1.0,
        1.0158861875534058
      ],
      "type": "Gaussian"
    }
  ]
}